[

    {"razonSocial":"Sancor","cuitCuil":26989177050,"telefono":2926453496, "email": "sancor.23@hotmail.com", "direccion": "Mitre 169"},
    {"razonSocial":"Dist. el colo","cuitCuil":26369177050,"telefono":2926449496, "email": "elcolo.dist@hotmail.com", "direccion": "Mitre 2596"},
    {"razonSocial":"Dist. San Martin","cuitCuil":26916837050,"telefono":2926453826, "email": "dist.martin@hotmail.com", "direccion": "Belgrano 1820"},
    {"razonSocial":"Tregar","cuitCuil":19889177050,"telefono":2926485496, "email": "tregar_dist@hotmail.com", "direccion": "Lamadrid 105"},
    {"razonSocial":"Don Yeyo","cuitCuil":26982467050,"telefono":2926453496, "email": "donyeyo.dist@hotmail.com", "direccion": "Lacunza 20"},
    {"razonSocial":"Dist Chirrus","cuitCuil":26989566050,"telefono":2926451966, "email": "chirrus@hotmail.com", "direccion": "Las Heras 266"},
    {"razonSocial":"Fabrica de hielo","cuitCuil":26919477050,"telefono":2926456936, "email": "hielo.23@hotmail.com", "direccion": "Sarmiento 1996"}

]